scryfall_set/__init__.py
scryfall_set/__main__.py
scryfall_set/cli.py
scryfall_set/db_insert.py
scryfall_set/db_queries.py
scryfall_set/db_setup.py
scryfall_set/loading.py
scryfall_set/main.py
scryfall_set/request.py
scryfall_set-0.2.dist-info/licenses/LICENCE
scryfall_set-0.2.dist-info/METADATA
scryfall_set-0.2.dist-info/WHEEL
scryfall_set-0.2.dist-info/entry_points.txt
scryfall_set-0.2.dist-info/top_level.txt
scryfall_set-0.2.dist-info/RECORD
