Metadata-Version: 2.4
Name: scryfall-set
Version: 0.2
Summary: Overview stats for MTG sets and searches using the Scryfall API
Author-email: thrly <o.thrly@gmail.com>
Project-URL: repository, https://github.com/thrly/scry
Project-URL: issues, https://github.com/thrly/scry/issues
Classifier: Programming Language :: Python :: 3
Classifier: Operating System :: OS Independent
Requires-Python: >=3.12
License-File: LICENCE
Requires-Dist: requests
Requires-Dist: pytest
Dynamic: license-file
